{"organizations": [], "uuid": "36c86e1aae353a338265564003f74a082944194b", "thread": {"social": {"gplus": {"shares": 0}, "pinterest": {"shares": 0}, "vk": {"shares": 0}, "linkedin": {"shares": 0}, "facebook": {"likes": 0, "shares": 0, "comments": 0}, "stumbledupon": {"shares": 0}}, "site_full": "www.terradaily.com", "main_image": "http://www.spxdaily.com/images-bg/typhoon-ma-on-japan-july-2011-afp-bg.jpg", "site_section": "http://www.terradaily.com/terradaily.xml", "section_title": "Earth News, Earth Science, Energy Technology, Environment News", "url": "http://www.terradaily.com/reports/Typhoon_Etau_slams_into_Japanese_mainland_999.html", "country": "US", "title": "Typhoon Etau slams into Japanese mainland", "performance_score": 0, "site": "terradaily.com", "participants_count": 0, "title_full": "Typhoon Etau slams into Japanese mainland", "spam_score": 0.0, "site_type": "news", "published": "2015-09-10T10:01:00.000+03:00", "replies_count": 0, "uuid": "36c86e1aae353a338265564003f74a082944194b"}, "author": "", "url": "http://www.terradaily.com/reports/Typhoon_Etau_slams_into_Japanese_mainland_999.html", "ord_in_thread": 0, "title": "Typhoon Etau slams into Japanese mainland", "locations": ["Tokyo"], "entities": {"persons": [], "locations": [], "organizations": []}, "highlightText": "", "language": "english", "persons": [], "text": "Typhoon Etau slams into Japanese mainland by Staff Writers Tokyo (AFP) Sept 9, 2015 \nTyphoon Etau slammed into Japan on Wednesday causing injuries as torrential rain sparked landslides and flooding with more than half a million people advised to evacuate, including in suburban Tokyo. \nRail and air services were also disrupted after the storm, packing winds of up to 125 kilometres (78 miles) per hour, landed in central Aichi prefecture shortly after 10:00 am local time (0100 GMT). \nTelevision footage showed cars sloshing through flooded streets and houses submerged, as pedestrians waded through water that reached their knees. \nSome areas had power outages and parts of Tokyo saw flooding as authorities advised about 900,000 people in the capital and other parts of the country to leave their homes because of the risk of landslides, public broadcaster NHK reported. \nLocal media said more than a dozen people were injured, including a 77-year-old woman who broke her leg after falling in strong winds. \nThe typhoon also disrupted air traffic, with at least 35 flights cancelled by Japan Airlines, All Nippon Airways and other budget rivals, NHK said, while some rail services were delayed. \nThe storm moved out into the Sea of Japan (East Sea) by the end of the day. \nLast month, powerful Typhoon Goni hit Japan's southernmost main island of Kyushu, killing at least one person, injuring 70 others, and disrupting rail and flight services. \noh/nf/pb/hg", "external_links": [], "published": "2015-09-10T10:01:00.000+03:00", "crawled": "2015-09-10T17:55:07.483+03:00", "highlightTitle": ""}