{"organizations": [], "uuid": "3ec6ef5e2fa06ca2ef0757649863a94a2ae91d96", "thread": {"social": {"gplus": {"shares": 0}, "pinterest": {"shares": 0}, "vk": {"shares": 0}, "linkedin": {"shares": 0}, "facebook": {"likes": 0, "shares": 0, "comments": 0}, "stumbledupon": {"shares": 0}}, "site_full": "www.freshnews.com", "main_image": "", "site_section": "http://freshnews.com//news/technology/feed", "section_title": "FreshNews.com - Technology News", "url": "http://www.freshnews.com/news/1128644/atec-wireless-unveils-dascad-tool-revolution-das-design-and-prediction", "country": "US", "title": "ATEC Wireless Unveils DASCAD Tool, a Revolution of DAS Design and Prediction", "performance_score": 0, "site": "freshnews.com", "participants_count": 1, "title_full": "ATEC Wireless Unveils DASCAD Tool, a Revolution of DAS Design and Prediction", "spam_score": 0.0, "site_type": "news", "published": "2015-09-16T15:00:00.000+03:00", "replies_count": 0, "uuid": "3ec6ef5e2fa06ca2ef0757649863a94a2ae91d96"}, "author": "admin", "url": "http://www.freshnews.com/news/1128644/atec-wireless-unveils-dascad-tool-revolution-das-design-and-prediction", "ord_in_thread": 0, "title": "ATEC Wireless Unveils DASCAD Tool, a Revolution of DAS Design and Prediction", "locations": [], "entities": {"persons": [], "locations": [], "organizations": []}, "highlightText": "", "language": "english", "persons": [], "text": "Companies mentioned in this article: Atec Wireless, LLC \nPARSIPPANY, N.J. -- (BUSINESS WIRE) -- Atec Wireless, LLC, announced today the launch of the beta version of DASCAD@ [ www.dascad.com ], a flagship In-Building design solution of Atec Group. DASCAD will provide wireless professionals the tools to carry out In-Building wireless networks design, budgeting, coverage prediction and project management. The new solution will also offer the necessary hardware required to perform coverage studies and network benchmark. \nDASCAD@ [ www.dascad.com ] is an innovative solution created to address the increasing demand for indoor coverage reliability and capacity which requires innovative testing and design techniques. DASCAD supports GSM / EDGE / GPRS / WCDMA / HSUPA / CDMA / EVDO / HSPA/ LTE and other wireless technologies. \nAhmed Abogendia, founder and CEO, quoted “DASCAD will revolutionize the In-Building wireless industry and we are very excited to be part of it.” \nAbout Atec Wireless, LLC: A leader in the wireless network design, deployment and optimization. For over a decade, Atec Wireless has assisted leading Telecom Operators and OEMs like AT&T, Ericsson, Huawei, Sprint, Verizon and Vodafone to build and maintain their networks globally. www.atecwireless.com . View source version on businesswire.com: http://www.businesswire.com/news/home/20150916005361/en/ Copyright © Business Wire 2015", "external_links": [], "published": "2015-09-16T15:00:00.000+03:00", "crawled": "2015-09-16T16:21:37.376+03:00", "highlightTitle": ""}