{"organizations": ["More Convergence Features Ubuntu Touch"], "uuid": "e77dbb5916fee62d313d3756f0f567c10655d6af", "thread": {"social": {"gplus": {"shares": 0}, "pinterest": {"shares": 0}, "vk": {"shares": 0}, "linkedin": {"shares": 0}, "facebook": {"likes": 0, "shares": 0, "comments": 0}, "stumbledupon": {"shares": 0}}, "site_full": "www.onenewspage.com", "main_image": "http://cdn.newsserve.net/i/20150917/784-Ubuntu-Touch-OTA-Gets-New-Unity.jpg", "site_section": "http://www.onenewspage.com/rss/latest/Technology.rss", "section_title": "Latest Technology News on One News Page", "url": "http://www.onenewspage.com/n/Technology/75589cqcp/Ubuntu-Touch-OTA-Gets-New-Unity.htm", "country": "US", "title": "Ubuntu Touch OTA-7 Gets New Unity 8, More Convergence Features", "performance_score": 0, "site": "onenewspage.com", "participants_count": 0, "title_full": "Ubuntu Touch OTA-7 Gets New Unity 8, More Convergence Features", "spam_score": 0.0, "site_type": "news", "published": "2015-09-18T00:12:00.000+03:00", "replies_count": 0, "uuid": "e77dbb5916fee62d313d3756f0f567c10655d6af"}, "author": "", "url": "http://www.onenewspage.com/n/Technology/75589cqcp/Ubuntu-Touch-OTA-Gets-New-Unity.htm", "ord_in_thread": 0, "title": "Ubuntu Touch OTA-7 Gets New Unity 8, More Convergence Features", "locations": [], "entities": {"persons": [], "locations": [], "organizations": []}, "highlightText": "", "language": "english", "persons": ["Łukasz Zemczak", "Zemczak"], "text": "Ubuntu Touch OTA-7 Gets New Unity 8, More Convergence Features Thursday, 17 September 2015 (18 minutes ago) Today, September 17, Canonical's Łukasz Zemczak sent in his daily report on the work done by the Ubuntu Touch developers for the upcoming major software update of the mobile operating system, OTA-7. According to Mr. Zemczak, the day of September 17 was a busy day for Ubuntu Touch developers as they managed to implement several new features, as well as to fix more of those annoying bugs that have been reported by users since the Ubuntu Touch OTA-6 update. Among the most i...", "external_links": [], "published": "2015-09-18T00:12:00.000+03:00", "crawled": "2015-09-18T00:25:06.094+03:00", "highlightTitle": ""}