{"organizations": [], "uuid": "0dd1eb968c19d86ab9ed0c770c022897b59a7d87", "thread": {"social": {"gplus": {"shares": 0}, "pinterest": {"shares": 0}, "vk": {"shares": 0}, "linkedin": {"shares": 0}, "facebook": {"likes": 0, "shares": 0, "comments": 0}, "stumbledupon": {"shares": 0}}, "site_full": "www.palmbeachpost.com", "main_image": "http://media.cmgdigital.com/shared/img/photos/2015/09/21/f4/0e/8840092_G.jpg", "site_section": "http://www.palmbeachpost.com/s/news/technology/", "section_title": "Technology | www.palmbeachpost.com", "url": "http://www.palmbeachpost.com/news/news/national/dad-kids-reel-483-lb-shark-cape-cod/nnj43/", "country": "US", "title": "Dad & kids reel in 483-lb. shark off Cape Cod", "performance_score": 0, "site": "palmbeachpost.com", "participants_count": 1, "title_full": "Dad & kids reel in 483-lb. shark off Cape Cod | www.palmbeachpost.com", "spam_score": 0.0, "site_type": "news", "published": "2015-09-21T19:19:00.000+03:00", "replies_count": 0, "uuid": "0dd1eb968c19d86ab9ed0c770c022897b59a7d87"}, "author": "Kacie Yearout", "url": "http://www.palmbeachpost.com/news/news/national/dad-kids-reel-483-lb-shark-cape-cod/nnj43/", "ord_in_thread": 0, "title": "Dad & kids reel in 483-lb. shark off Cape Cod", "locations": [], "entities": {"persons": [], "locations": [], "organizations": []}, "highlightText": "", "language": "english", "persons": [], "text": "They went out to catch some tuna, but Mike Evensen and his kids reeled something much bigger.\nThey were fishing off the coast of Provincetown, Massachusetts, Sunday when they landed a porbeagle shark. Evensen said it took them an hour to reel the shark toward the boat. They then harpooned it and it took another hour to hand line it into the boat.\n( Credit: Mike Evensen) Evensen said when he saw the white patch by the dorsal fin, he knew it was a porbeagle.\nWhile he was reeling it in in, his son, Cameron, 9, helped man the boat. Both Cameron and Hanna took turns reeling in the shark.\nOnce back to the dock, the Division of Marine Fisheries came to take the shark apart and weigh it. In total, it weighed 483 pounds, just shy of the 490-pound state record.\nThe shark was cut up into steaks and Mark Evensen and his family now have about 200 pounds of shark meat to eat.\nTrending on Facebook\n6-month-old baby found dead in teacher’s car in Deltona, Fla. Report: Mom, boyfriend kept body of 'Baby Doe' refrigerated before dumping her Woman finds copperhead snake sliding down her door while driving Hero 5th-grader rescues students after bus careens into pond Advertisers drop 'The View' after #NursesUnite controversy More popular and trending stories\n</p", "external_links": ["https://www.facebook.com/CMGNationalNews", "http://media.cmgdigital.com/shared/lt/lt_cache/thumbnail/600/img/photos/2015/09/21/8b/c5/8840110_G.jpg"], "published": "2015-09-21T19:19:00.000+03:00", "crawled": "2015-09-21T18:42:08.228+03:00", "highlightTitle": ""}