{"organizations": ["CBI"], "uuid": "09055123718dc1afddb7c653beaa537ddc9b1c2f", "thread": {"social": {"gplus": {"shares": 0}, "pinterest": {"shares": 0}, "vk": {"shares": 0}, "linkedin": {"shares": 0}, "facebook": {"likes": 0, "shares": 0, "comments": 0}, "stumbledupon": {"shares": 0}}, "site_full": "www.industriesnews.net", "main_image": "", "site_section": "http://www.industriesnews.net/rss.php/?ind=technology", "section_title": "industriesnews.net  - Breaking Technology News latest RSS headlines", "url": "http://www.industriesnews.net/story?sid=s236357825&ampcid=400", "country": "US", "title": "CBI registers six more FIRs in Vyapam case", "performance_score": 0, "site": "industriesnews.net", "participants_count": 0, "title_full": "CBI registers six more FIRs in Vyapam case", "spam_score": 0.0, "site_type": "news", "published": "2015-09-02T19:09:00.000+03:00", "replies_count": 0, "uuid": "09055123718dc1afddb7c653beaa537ddc9b1c2f"}, "author": "", "url": "http://www.industriesnews.net/story?sid=s236357825&ampcid=400", "ord_in_thread": 0, "title": "CBI registers six more FIRs in Vyapam case", "locations": ["Vyapam"], "entities": {"persons": [], "locations": [], "organizations": []}, "highlightText": "", "language": "english", "persons": [], "text": "CBI registers six more FIRs in Vyapam case \nTechnology Industry News.Net (IANS) : Wednesday 2nd September, 2015 \nThe CBI on Wednesday registered six fresh FIRs in its probe into the Vyapam scam in Madhya Pradesh. \nThe first case was registered against two accused on the allegations of cheating by impersonation in Constable Recruitment Examination 2013, the CBI said in a release. \nThe Central Bureau of Investigation (CBI) registered the second case against nine accused on the allegations of cheating by impersonation in Constable Recruitment Examination 2012 conducted by Vyavsayik Pariksha Mandal (Vyapam), or the Madhya Pradesh Professional Examination Board (MPPEB). \nThe third case was registered against four accused on the allegations of cheating by impersonation in Forest Guard Recruitment Examination 2013. \nThe fourth case was registered against 16 accused on the allegations of cheating by impersonation in Pre Medical Test 2009. \nThree accused were booked in the fifth case on the allegations of cheating by impersonation in Constable Recruitment Examination 2012. \nThe sixth case was registered against two accused on allegations of cheating by impersonation in Police Constable Recruitment Exam 2013. \nThe CBI has already registered 95 FIRs and launched 14 preliminary inquiries into the Vyapam scam. \nThe Supreme Court on July 9 handed over the Vyapam cases to the central investigating agency. Over 40 people linked with the scam have died under mysterious circumstances or committed suicide. More Technology Industry News  ", "external_links": [], "published": "2015-09-02T19:09:00.000+03:00", "crawled": "2015-09-03T09:20:44.402+03:00", "highlightTitle": ""}