{"organizations": [], "uuid": "967ee89cdc61c51c5a5ea6de270a4016c19b1503", "thread": {"social": {"gplus": {"shares": 0}, "pinterest": {"shares": 0}, "vk": {"shares": 0}, "linkedin": {"shares": 0}, "facebook": {"likes": 0, "shares": 0, "comments": 0}, "stumbledupon": {"shares": 0}}, "site_full": "www.freshnews.com", "main_image": "", "site_section": "http://freshnews.com//news/technology/feed", "section_title": "FreshNews.com - Technology News", "url": "http://www.freshnews.com/news/1124261/lifelock-present-upcoming-conferences", "country": "US", "title": "LifeLock to Present at Upcoming Conferences", "performance_score": 0, "site": "freshnews.com", "participants_count": 1, "title_full": "LifeLock to Present at Upcoming Conferences", "spam_score": 0.0, "site_type": "news", "published": "2015-09-03T23:05:00.000+03:00", "replies_count": 0, "uuid": "967ee89cdc61c51c5a5ea6de270a4016c19b1503"}, "author": "admin", "url": "http://www.freshnews.com/news/1124261/lifelock-present-upcoming-conferences", "ord_in_thread": 0, "title": "LifeLock to Present at Upcoming Conferences", "locations": [], "entities": {"persons": [], "locations": [], "organizations": []}, "highlightText": "", "language": "english", "persons": [], "text": "Submitted by admin on 9/3/2015 @ 1:05 PM Companies mentioned in this article: LifeLock, Inc. \nTEMPE, Ariz. -- (BUSINESS WIRE) -- LifeLock, Inc . (NYSE:LOCK), an industry leader in identity theft protection, today announced that Todd Davis, Chairman and Chief Executive Officer, and Chris Power, Chief Financial Officer, will present at the Citi Global Technology Conference in New York City. This presentation is scheduled for Wednesday, September 9, 2015 at 9:30 a.m. Eastern Time, or 6:30 a.m. Pacific Time. \nTodd Davis, Chris Power, and Hilary Schneider, President, will present at the Deutsche Bank Technology, Media, and Telecom Conference in Las Vegas, NV. This presentation is scheduled for Thursday, September 17, 2015 at 6:20 p.m. Eastern Time, or 3:20 p.m. Pacific Time. \nBoth events will be live webcasts and accessible from the investor relations page of the LifeLock website at http://investor.lifelock.com/ . Following the events, replays will be made available at the same location. \nAbout LifeLock \nLifeLock, Inc. (NYSE:LOCK) is a leading provider of proactive identity theft protection services for consumers and consumer risk management services for enterprises. LifeLock’s threat detection, proactive identity alerts, and comprehensive remediation services help provide peace of mind for consumers amid the growing threat of identity theft. Leveraging unique data, science and patented technology from ID Analytics, LLC., a wholly owned subsidiary, LifeLock offers identity theft protection that goes significantly beyond credit monitoring. As part of its commitment to help fight identity theft, LifeLock works to train law enforcement and partners with a variety of non-profit organizations to help consumers establish positive habits to combat this threat. View source version on businesswire.com: http://www.businesswire.com/news/home/20150903006114/en/ Copyright © Business Wire 2015", "external_links": [], "published": "2015-09-03T23:05:00.000+03:00", "crawled": "2015-09-04T00:04:42.142+03:00", "highlightTitle": ""}