{"organizations": [], "uuid": "ab7593c45a859130e7c8a7491a5b1299b24135f0", "thread": {"social": {"gplus": {"shares": 0}, "pinterest": {"shares": 0}, "vk": {"shares": 0}, "linkedin": {"shares": 0}, "facebook": {"likes": 0, "shares": 0, "comments": 0}, "stumbledupon": {"shares": 0}}, "site_full": "www.securenigeria365.com", "main_image": "http://i2.wp.com/www.securenigeria365.com/wp-content/uploads/2015/09/Buhari_21.jpg?resize=800%2C500", "site_section": "http://www.securenigeria365.com/feed/", "section_title": "Secure Nigeria 365 - Latest news updates in NIgeria including niger delta, business, politics, entertainment, fashion, health, technology, naija lifestyle", "url": "http://www.securenigeria365.com/president-buhari-prays-eid-el-kabir-in-daura/", "country": "", "title": "President Buhari prays Eid El-Kabir in Daura", "performance_score": 0, "site": "securenigeria365.com", "participants_count": 1, "title_full": "President Buhari prays Eid El-Kabir in Daura", "spam_score": 0.0, "site_type": "news", "published": "2015-09-24T21:03:00.000+03:00", "replies_count": 0, "uuid": "ab7593c45a859130e7c8a7491a5b1299b24135f0"}, "author": "Secure Nigeria 365", "url": "http://www.securenigeria365.com/president-buhari-prays-eid-el-kabir-in-daura/", "ord_in_thread": 0, "title": "President Buhari prays Eid El-Kabir in Daura", "locations": [], "entities": {"persons": [], "locations": [], "organizations": []}, "highlightText": "", "language": "english", "persons": [], "text": "tweet \nPresident Muhammadu Buhari on Thursday joined Muslims faithful in observing the Eid-el-kabir prayer at his native home, Daura, Katsina State. \nThe prayer was led by the Chief Imam of Daura, Sheikh Safiyanu Yusuf, at Kofar-Arewa Eid ground around 9.30 a.m. \nIn his sermon, the Imam stressed the importance of sacrifice in Islam. He said that the sacrifice could be done win ram, sheep, goat, cow or camel. Yusuf said that the meat could be given to the needy and even non Muslims. \nHe urged people to continue to pray to the almighty Allah to give the country peace, unity and stability. The Emir of Daura, Alhaji Umar Farouq, directed all mosques in the emirate to organise special prayer for peace and stability in the nation. \nHe prayed to Allah to continue to guide the President to be able to lead the country right. \n‘’We need to intensify prayer for peace and stability in the country, because nothing can be achieved without peace,’’ he said. \nSome of the important personalities who observed the Eid prayer include Director, Department of Security Service (DSS), Alhaji Lawal Musa Daura, and other prominent sons of the emirate including religious and traditional leaders among others. \nThe News Agency of Nigeria (NAN) reports that President Buhari and the Emir slaughtered their rams after the prayer at the Eid ground. \nNAN also observed that there was adequate security at the Eid ground and the prayer ended peacefully.", "external_links": [], "published": "2015-09-24T21:03:00.000+03:00", "crawled": "2015-09-25T03:01:56.758+03:00", "highlightTitle": ""}