{"organizations": [], "uuid": "fa164a8dda2c6c34f9656c9d3daef0098274bf0d", "thread": {"social": {"gplus": {"shares": 0}, "pinterest": {"shares": 0}, "vk": {"shares": 0}, "linkedin": {"shares": 0}, "facebook": {"likes": 0, "shares": 0, "comments": 0}, "stumbledupon": {"shares": 0}}, "site_full": "feeds.reuters.com", "main_image": "", "site_section": "http://feeds.reuters.com/reuters/technologysectorNews", "section_title": "Reuters: Technology", "url": "http://feeds.reuters.com/~r/reuters/technologysectorNews/~3/AMLw75VNdkU/story01.htm", "country": "US", "title": "TronicS Microsystems H1 net result group share swings to loss of 1.2 mln euros", "performance_score": 0, "site": "reuters.com", "participants_count": 1, "title_full": "BRIEF-TronicS Microsystems H1 net result group share swings to loss of 1.2 mln euros | Reuters", "spam_score": 0.0, "site_type": "news", "published": "2015-09-09T09:48:00.000+03:00", "replies_count": 0, "uuid": "fa164a8dda2c6c34f9656c9d3daef0098274bf0d"}, "author": "Reuters", "url": "http://feeds.reuters.com/~r/reuters/technologysectorNews/~3/AMLw75VNdkU/story01.htm", "ord_in_thread": 0, "title": "TronicS Microsystems H1 net result group share swings to loss of 1.2 mln euros", "locations": [], "entities": {"persons": [], "locations": [], "organizations": []}, "highlightText": "", "language": "english", "persons": [], "text": "Sept 9 TronicS Microsystems SA :\n* H1 current operating loss 1.1 million euros ($1.2 million)versus profit of 0.2 million euros a year ago\n* H1 net loss group share 1.2 million euros versus profit of 79,000 euros a year ago\n* Sees profitable growth from H1 2016\n* Confirms 2018 revenue target of 40 million euros\nSource text for Eikon: ($1 = 0.8962 euros) (Gdynia Newsroom)", "external_links": [], "published": "2015-09-09T09:48:00.000+03:00", "crawled": "2015-09-09T10:10:46.276+03:00", "highlightTitle": ""}